pydnb/VERSION
pydnb/__init__.py
pydnb/dnb.py
pydnb/utils.py
pydnb-0.0.1.dist-info/METADATA
pydnb-0.0.1.dist-info/RECORD
pydnb-0.0.1.dist-info/WHEEL
pydnb-0.0.1.dist-info/top_level.txt
