Metadata-Version: 2.1
Name: pydnb
Version: 0.0.1
Summary: Implementation of dynamic naive Bayes classifier (extension of hidden Markov model)
Home-page: https://github.com/tsabata/PyDNB
Author: Tomas Sabata
Author-email: sabata.tomas@mail.com
License: MIT
Platform: UNKNOWN
Classifier: Programming Language :: Python :: 3
Requires-Python: >=3.4
Requires-Dist: numpy
Requires-Dist: scipy
Requires-Dist: pandas
